{
    "transaction": {
        "cartId": "G8MA7TZHII",
        "sequenceNumber": 426,
        "cartInfo": {
            "businessDate": "2023-09-12",
            "beginDateTime": "2023-09-12T15:48:46.567",
            "status": "Itemization",
            "totals": {
                "grandAmount": 34.03,
                "netAmount": 30.85,
                "taxAmounts": {
                    "taxAmount": 3.18,
                    "itemFee": 0,
                    "transactionFee": 0
                },
                "itemsCount": 2,
                "balanceDue": 34.03,
                "discountAmount": 0,
                "grossAmount": 0
            },
            "defaultCurrency": "USD"
        },
        "manualSegments": [],
        "items": [
            {
                "lineItem": {
                    "EntryMethod": "Automatic",
                    "itemId": {
                        "value": "20",
                        "type": "SKU"
                    },
                    "quantity": {
                        "value": 1
                    }
                },
                "fullDescription": "Arak",
                "description": "Arak",
                "itemType": "Stock",
                "lineId": 1,
                "amount": 18.849999999999998,
                "extendedAmount": 17.65,
                "securityScale": true,
                "imageUrl": "",
                "entryMode": "BarcodeOrder",
                "price": {
                    "unitPrice": 17.65,
                    "currency": "USD",
                    "quantity": 1
                },
                "netAmount": 17.65,
                "regularPrice": {
                    "unitPrice": 17.65,
                    "currency": "USD",
                    "quantity": 1
                },
                "status": "Active",
                "taxes": [
                    {
                        "lineId": 1,
                        "authorityId": "First Authority",
                        "amount": 1.77,
                        "taxableAmount": 17.65,
                        "exemptAmount": 0
                    },
                    {
                        "lineId": 2,
                        "authorityId": "First Authority",
                        "amount": 1.41,
                        "taxableAmount": 17.65,
                        "exemptAmount": 0
                    }
                ],
                "itemIndicators": [
                    "C"
                ],
                "itemBatchInfo": {
                    "type": "QRCodeOrder",
                    "label": "PH",
                    "identifier": "3400001371",
                    "grouping": true
                },
                "linkedLines": [
                    {
                        "lineItem": {
                            "EntryMethod": "Automatic",
                            "itemId": {
                                "value": "7991439",
                                "type": "SKU"
                            },
                            "quantity": {
                                "value": 1,
                                "entryMethod": "Automatic"
                            }
                        },
                        "fullDescription": "Long Deposit Bottle Bottle 75cc",
                        "description": "Deposit Bottle Bottle 75cc",
                        "itemType": "Deposit",
                        "lineId": 2,
                        "amount": 1.2,
                        "extendedAmount": 1.2,
                        "securityScale": true,
                        "imageUrl": "",
                        "entryMode": "BarcodeOrder",
                        "price": {
                            "unitPrice": 1.2,
                            "currency": "USD",
                            "quantity": 1
                        },
                        "netAmount": 1.2,
                        "regularPrice": {
                            "unitPrice": 1.2,
                            "currency": "USD",
                            "quantity": 1
                        },
                        "status": "Active",
                        "taxes": [],
                        "itemBatchInfo": {
                            "type": "QRCodeOrder",
                            "label": "PH",
                            "identifier": "3400001371",
                            "grouping": true
                        }
                    }
                ]
            },
            {
                "lineItem": {
                    "EntryMethod": "Automatic",
                    "itemId": {
                        "value": "3",
                        "type": "SKU"
                    },
                    "quantity": {
                        "value": 1
                    }
                },
                "fullDescription": "Long Banana",
                "description": "Banana",
                "itemType": "Stock",
                "lineId": 3,
                "amount": 12,
                "extendedAmount": 12,
                "securityScale": true,
                "imageUrl": "",
                "entryMode": "BarcodeOrder",
                "price": {
                    "unitPrice": 12,
                    "currency": "USD",
                    "quantity": 1
                },
                "netAmount": 12,
                "regularPrice": {
                    "unitPrice": 12,
                    "currency": "USD",
                    "quantity": 1
                },
                "status": "Active",
                "taxes": [],
                "itemBatchInfo": {
                    "type": "QRCodeOrder",
                    "label": "PH",
                    "identifier": "3400001371",
                    "grouping": true
                }
            }
        ],
        "rewards": [],
        "coupons": [],
        "payments": [],
        "returns": [],
        "identifiers": {
            "taxExempt": false,
            "taxDiscount": false,
            "accessorialFlag": false,
            "returnType": "NoneReceiptedReturn",
            "isWic": false,
            "isWicCvv": false,
            "typeCode": "SaleTransaction"
        },
        "ewicReceipts": [],
        "receipts": []
    }
}