[
  {
    "name": "NCR Expense 23",
    "description": "NCR Expense account 23",
    "retailStoreId": "1",
    "profileName": "Income and Expense",
    "externalId": "f14b59dc-979f-4f93-b3ed-4cf3a20e609a",
    "profileExternalId": "995",
    "profileDescription": "Income And ExpenseAccount Profile",
    "profileIsTaxable": true

  },
  {
    "name": "NCR Income 23",
    "description": "NCR Income account 23",
    "retailStoreId": "1",
    "profileName": "Income and Expense",
    "externalId": "3928f0be-1f1e-40f0-801b-1c79574a55fa",
    "profileExternalId": "995",
    "profileDescription": "Income And ExpenseAccount Profile",
    "profileIsTaxable": true

  },
  {
    "name": "NCR Income and Expense 23",
    "description": "NCR Income and Expense account 23",
    "retailStoreId": "1",
    "profileName": "Income and Expense",
    "externalId": "af0d2e01-d0b7-4df9-8420-b0a5f06d7a19",
    "profileExternalId": "995",
    "profileDescription": "Income And ExpenseAccount Profile",
    "profileIsTaxable": true

  },
  {
    "name": "PrePay Income and Expense account",
    "description": "PrePay Income and Expense account",
    "retailStoreId": "1",
    "profileName": "Income and Expense",
    "externalId": "2405adf3-adf1-43d1-95f5-a3841e65ea74",
    "profileExternalId": "993",
    "profileDescription": "PrePay Account Profile",
    "profileIsTaxable": true

  },
  {
    "name": "Sellable Media account",
    "description": "Sellable Media Income and Expense account",
    "retailStoreId": "1",
    "profileName": "Income and Expense",
    "externalId": "7cb5cb67-2fc4-40db-8a16-a28c83735d11",
    "profileExternalId": "983",
    "profileDescription": "SellableMedia Account Profile",
    "profileIsTaxable": true

  }
]