{
  "cartInfo": {
      "status": "Itemization",
      "totals": {
          "netAmount": 0,
          "taxAmounts": {
              "taxAmount": 0,
              "included": 0,
              "itemFee": 0,
              "transactionFee": 0,
              "taxExemptAmount": 0
          },
          "balanceDue": 0,
          "cashbackAmount": 0,
          "discountAmount": 0,
          "itemsCount": 0
      },
      "defaultCurrency": "USD"
  },
  "cartId": "Df56zJaUukyOQN9Po6pIIA",
  "isTransactionTotaled": false,
  "sequenceNumber": 5870,
  "items": [
      {
          "lineItem": {
              "itemId": {
                  "type": "0",
                  "value": "103",
                  "id": "00000000001030"
              },
              "quantity": {
                  "unitOfMeasure": "EA",
                  "value": 1
              }
          },
          "extendedAmount": 10,
          "itemType": "Normal",
          "lineId": 1,
          "status": "Cancelled",
          "fullDescription": "sprite",
          "description": "sprite",
          "price": {
              "unitOfMeasure": "EA",
              "specialPrice": false,
              "unitPrice": 10,
              "quantity": 1
          },
          "regularPrice": {
              "unitPrice": 10
          },
          "amount": 10,
          "securityScale": true,
          "entryMethod": "Keyed",
          "sequence": "638043614049170380"
      }
  ],
  "payments": [],
  "surcharges": [],
  "receipts": [],
  "returns": [],
  "refunds": [],
  "rewards": [],
  "coupons": [],
  "restrictions": [],
  "customerPrograms": [],
  "identifiers": {}
}