{
    "cartId": "VO3D9H6LUN",
    "sequenceNumber": 564,
    "cartInfo": {
        "businessDate": "2024-04-21",
        "beginDateTime": "2024-04-21T17:26:05.256",
        "status": "Itemization",
        "totals": {
            "grandAmount": 12,
            "netAmount": 12,
            "taxAmounts": {
                "taxAmount": 0,
                "itemFee": 0,
                "transactionFee": 0
            },
            "itemsCount": 1,
            "balanceDue": 12,
            "discountAmount": 0,
            "grossAmount": 0
        },
        "defaultCurrency": "USD"
    },
    "manualSegments": [],
    "items": [],
    "rewards": [],
    "coupons": [],
    "payments": [],
    "returns": [],
    "identifiers": {
        "taxExempt": false,
        "taxDiscount": false,
        "accessorialFlag": false,
        "returnType": "NoneReceiptedReturn",
        "isWic": false,
        "isWicCvv": false,
        "typeCode": "SaleTransaction"
    },
    "ewicReceipts": [],
    "receipts": []
}